{
  "query": "How does cool climate affect acidity?",
  "generated_at": "2026-05-24T17:47:47+00:00",
  "governance_filter_applied": true,
  "query_analysis": {
    "query_intent": "cause_effect_explanation",
    "reasoning_intent": "cause_effect",
    "matched_terms": [
      {
        "canonical_term": "climate",
        "category": "climate"
      },
      {
        "canonical_term": "cool climate",
        "category": "climate"
      },
      {
        "canonical_term": "acidity",
        "category": "sat_term"
      }
    ],
    "matched_concepts": [
      {
        "id": "C_ACIDITY",
        "name": "Acidity",
        "terms": [
          "acidity",
          "acidity ageability",
          "balance",
          "cool climate",
          "cool climate acidity",
          "high acidity",
          "lower ph",
          "malic acid",
          "malolactic conversion",
          "mlf acidity",
          "tartaric acid"
        ]
      },
      {
        "id": "C_COOL_CLIMATE",
        "name": "Cool Climate",
        "terms": [
          "cool climate",
          "cool climate acidity",
          "cool climate alcohol",
          "cool climate aroma",
          "growing season",
          "malic acid",
          "slow ripening"
        ]
      }
    ],
    "matched_causal_chains": [
      {
        "id": "CC_COOL_CLIMATE_ACIDITY",
        "name": "Cool climate → high acidity in finished wine",
        "terms": [
          "acid retention",
          "acidity",
          "cold climate",
          "cool climate",
          "cool climate acidity",
          "cool climate → high acidity in finished wine",
          "freshness",
          "growing season",
          "high acidity",
          "high altitude",
          "higher acidity",
          "lower ph",
          "malic acid",
          "slow ripening",
          "slower ripening",
          "tartaric acid"
        ]
      },
      {
        "id": "CC_COOL_CLIMATE_ALCOHOL",
        "name": "Cool climate → limited sugar accumulation → lower potential alcohol",
        "terms": [
          "cool climate",
          "cool climate alcohol",
          "cool climate → limited sugar accumulation → lower potential alcohol",
          "growing season",
          "length"
        ]
      },
      {
        "id": "CC_COOL_CLIMATE_AROMA",
        "name": "Cool climate → slower ripening → primary aroma profile (citrus/green fruit/floral)",
        "terms": [
          "cool climate",
          "cool climate aroma",
          "cool climate → slower ripening → primary aroma profile (citrus/green fruit/floral)",
          "growing season",
          "higher acidity",
          "slower ripening"
        ]
      }
    ],
    "matched_relationships": [
      {
        "id": "R_COOL_CLIMATE__INCREASES__ACIDITY",
        "name": "cool climate acidity",
        "terms": [
          "acidity",
          "cool climate",
          "cool climate acidity",
          "growing season",
          "lower ph",
          "malic acid",
          "slower ripening",
          "tartaric acid"
        ]
      },
      {
        "id": "R_COOL_CLIMATE__OFTEN_CONFUSED_WITH__UNDER_RIPE",
        "name": "cool climate under ripe",
        "terms": [
          "balance",
          "cool climate",
          "cool climate under ripe",
          "high acidity",
          "malic acid"
        ]
      },
      {
        "id": "R_MALOLACTIC_CONVERSION__REDUCES__ACIDITY",
        "name": "malolactic conversion acidity",
        "terms": [
          "acidity",
          "cool climate",
          "malic acid",
          "malolactic conversion",
          "malolactic conversion acidity",
          "tartaric acid"
        ]
      }
    ],
    "matched_misconceptions": [
      {
        "id": "MC_ACIDITY_01",
        "name": "High acidity in a wine means the wine is low quality or unpleasant.",
        "terms": [
          "acidity",
          "acidity 01",
          "balance",
          "cool climate",
          "high acidity",
          "high acidity in a wine means the wine is low quality or unpleasant.",
          "intensity"
        ]
      },
      {
        "id": "MC_COOL_CLIMATE_01",
        "name": "Cool climate wines are always low in alcohol.",
        "terms": [
          "cool climate",
          "cool climate 01",
          "cool climate wines are always low in alcohol."
        ]
      },
      {
        "id": "MC_COOL_CLIMATE_02",
        "name": "Cool climate wines always have green, unripe flavours.",
        "terms": [
          "cool climate",
          "cool climate 02",
          "cool climate wines always have green, unripe flavours."
        ]
      }
    ],
    "query_expansion_terms": [
      "acid",
      "acid retention",
      "acidity",
      "acidity 01",
      "acidity ageability",
      "balance",
      "climate",
      "cold climate",
      "cool climate",
      "cool climate 01",
      "cool climate 02",
      "cool climate acidity",
      "cool climate alcohol",
      "cool climate aroma",
      "cool climate under ripe",
      "cool climate wines always have green, unripe flavours.",
      "cool climate wines are always low in alcohol.",
      "cool climate → high acidity in finished wine",
      "cool climate → limited sugar accumulation → lower potential alcohol",
      "cool climate → slower ripening → primary aroma profile (citrus/green fruit/floral)",
      "crispness",
      "freshness",
      "growing season",
      "high acidity",
      "high acidity in a wine means the wine is low quality or unpleasant.",
      "high altitude",
      "higher acidity",
      "intensity",
      "length",
      "low temperature",
      "low temperatures",
      "lower ph",
      "malic acid",
      "malolactic conversion",
      "malolactic conversion acidity",
      "mlf acidity",
      "slow ripening",
      "slower ripening",
      "tartaric acid"
    ],
    "query_tokens": [
      "acidity",
      "affect",
      "climate",
      "cool"
    ],
    "expanded_query_tokens": [
      "accumulation",
      "acid",
      "acidity",
      "affect",
      "ageability",
      "alcohol",
      "altitude",
      "always",
      "aroma",
      "balance",
      "citrus",
      "climate",
      "cold",
      "conversion",
      "cool",
      "crispness",
      "finished",
      "flavours",
      "floral",
      "freshness",
      "fruit",
      "green",
      "growing",
      "have",
      "high",
      "higher",
      "intensity",
      "length",
      "limited",
      "low",
      "lower",
      "malic",
      "malolactic",
      "means",
      "mlf",
      "ph",
      "potential",
      "primary",
      "profile",
      "quality",
      "retention",
      "ripe",
      "ripening",
      "season",
      "slow",
      "slower",
      "sugar",
      "tartaric",
      "temperature",
      "temperatures",
      "under",
      "unpleasant",
      "unripe",
      "wine",
      "wines"
    ]
  },
  "indexed_chunks": 385,
  "excluded_chunks": 0,
  "golden_chunks_loaded": 166,
  "dictionary_terms_loaded": 424,
  "knowledge_nodes_loaded": 76,
  "top_k": 5,
  "retrieved_chunks": [
    {
      "chunk_id": "OFFICIAL_WSET_1_1_THE_SYSTEMATIC_APPROACH_TO_TASTING_WINE_001",
      "score": 1.0,
      "source_video": "",
      "source_filename": "4-1_1_the_systematic_approach_to_tasting_wine.md",
      "source_type": "official_wset_extracted",
      "source_file": "knowledge/official-wset/study-guide/wset_markdown/seccion_4_section_1_wine_and_the_consumer/4-1_1_the_systematic_approach_to_tasting_wine.md",
      "source_trust_tier": 1,
      "title": "1 The Systematic Approach to Tasting Wine®",
      "section": "4",
      "subtopic": "4.1",
      "official_grading_authority": false,
      "requires_human_review": true,
      "reasoning_type": "cause_effect",
      "pedagogical_role": "official_reference",
      "retrieval_priority": "none",
      "matched_terms": [
        "acid",
        "acidity",
        "affect",
        "balance",
        "climate",
        "cool",
        "freshness",
        "high acidity",
        "higher acidity",
        "intensity",
        "length",
        "malic acid"
      ],
      "matched_concepts": [
        "Acidity",
        "Cool Climate",
        "acidity",
        "balance",
        "high acidity",
        "malic acid"
      ],
      "matched_causal_chains": [
        "Cool climate → high acidity in finished wine",
        "Cool climate → limited sugar accumulation → lower potential alcohol",
        "Cool climate → slower ripening → primary aroma profile (citrus/green fruit/floral)",
        "acidity",
        "freshness",
        "high acidity",
        "higher acidity",
        "length"
      ],
      "matched_dictionary_terms": [
        "acidity",
        "climate"
      ],
      "query_expansion_terms": [
        "acid",
        "acid retention",
        "acidity",
        "acidity 01",
        "acidity ageability",
        "balance",
        "climate",
        "cold climate",
        "cool climate",
        "cool climate 01",
        "cool climate 02",
        "cool climate acidity",
        "cool climate alcohol",
        "cool climate aroma",
        "cool climate under ripe",
        "cool climate wines always have green, unripe flavours.",
        "cool climate wines are always low in alcohol.",
        "cool climate → high acidity in finished wine",
        "cool climate → limited sugar accumulation → lower potential alcohol",
        "cool climate → slower ripening → primary aroma profile (citrus/green fruit/floral)",
        "crispness",
        "freshness",
        "growing season",
        "high acidity",
        "high acidity in a wine means the wine is low quality or unpleasant.",
        "high altitude",
        "higher acidity",
        "intensity",
        "length",
        "low temperature",
        "low temperatures",
        "lower ph",
        "malic acid",
        "malolactic conversion",
        "malolactic conversion acidity",
        "mlf acidity",
        "slow ripening",
        "slower ripening",
        "tartaric acid"
      ],
      "knowledge_graph_boost_applied": true,
      "why_retrieved": [
        "matched canonical/query terms: acid, acidity, affect, balance, climate, cool, freshness, high acidity",
        "aligns with cause_effect reasoning intent",
        "matched SAT/tasting vocabulary",
        "supports cause/effect explanation",
        "matches knowledge-map concept or relationship terms",
        "matches knowledge-map causal-chain mechanism",
        "matches knowledge-map concept vocabulary",
        "official WSET extracted Tutor support",
        "matched official section/topic metadata",
        "exact term match"
      ],
      "text_excerpt": "# 1 The Systematic Approach to Tasting Wine® <!-- página 10 --> THES YSTEMATICA PPROACHT OT ASTINGW INE\" TheS ystematiAc pproactho TastinWg ine® The WSET Level 3. Syst~matic Approach to Tasting Wine (SAT) is a tool that allows you to write a complete description of a wine and then use this information to make an evaluation of its quality and readiness for...",
      "scoring_breakdown": {
        "lexical_overlap": 0.18,
        "expanded_lexical_overlap": 0.0673,
        "canonical_dictionary_terms": 0.08,
        "dictionary_category_match": 0.0,
        "golden_chunk_boost": 0.0,
        "reasoning_type_alignment": 0.091,
        "pedagogical_role_alignment": 0.0,
        "retrieval_priority_boost": 0.0,
        "sat_term_boost": 0.09,
        "cause_effect_boost": 0.1,
        "exam_strategy_boost": 0.0,
        "knowledge_graph_match": 0.1,
        "causal_chain_match": 0.0711,
        "concept_match": 0.06,
        "source_concept_phrase_match": 0.0,
        "official_source_boost": 0.18,
        "exact_term_match_boost": 0.08,
        "section_topic_match_boost": 0.0133,
        "official_exam_register_boost": 0.06,
        "quality_flags_penalty": -0.0
      },
      "safe_for_examiner": false,
      "agent_corpus": "tutor"
    },
    {
      "chunk_id": "OFFICIAL_WSET_4_7_COMMON_ELEMENTS_IN_WINEMAKING_AND_MATURATION_001",
      "score": 1.0,
      "source_video": "",
      "source_filename": "5-4_7_common_elements_in_winemaking_and_maturation.md",
      "source_type": "official_wset_extracted",
      "source_file": "knowledge/official-wset/study-guide/wset_markdown/seccion_5_section_2_factors_affecting_the_style_quality_and_price_of_w/5-4_7_common_elements_in_winemaking_and_maturation.md",
      "source_trust_tier": 1,
      "title": "7 Common Elements in Winemaking and Maturation",
      "section": "5",
      "subtopic": "5.4",
      "official_grading_authority": false,
      "requires_human_review": true,
      "reasoning_type": "cause_effect",
      "pedagogical_role": "official_reference",
      "retrieval_priority": "none",
      "matched_terms": [
        "acid",
        "acidity",
        "affect",
        "balance",
        "climate",
        "cool",
        "freshness",
        "length",
        "tartaric acid"
      ],
      "matched_concepts": [
        "Acidity",
        "acidity",
        "balance",
        "tartaric acid"
      ],
      "matched_causal_chains": [
        "Cool climate → high acidity in finished wine",
        "Cool climate → limited sugar accumulation → lower potential alcohol",
        "acidity",
        "freshness",
        "length",
        "tartaric acid"
      ],
      "matched_dictionary_terms": [
        "acidity",
        "climate"
      ],
      "query_expansion_terms": [
        "acid",
        "acid retention",
        "acidity",
        "acidity 01",
        "acidity ageability",
        "balance",
        "climate",
        "cold climate",
        "cool climate",
        "cool climate 01",
        "cool climate 02",
        "cool climate acidity",
        "cool climate alcohol",
        "cool climate aroma",
        "cool climate under ripe",
        "cool climate wines always have green, unripe flavours.",
        "cool climate wines are always low in alcohol.",
        "cool climate → high acidity in finished wine",
        "cool climate → limited sugar accumulation → lower potential alcohol",
        "cool climate → slower ripening → primary aroma profile (citrus/green fruit/floral)",
        "crispness",
        "freshness",
        "growing season",
        "high acidity",
        "high acidity in a wine means the wine is low quality or unpleasant.",
        "high altitude",
        "higher acidity",
        "intensity",
        "length",
        "low temperature",
        "low temperatures",
        "lower ph",
        "malic acid",
        "malolactic conversion",
        "malolactic conversion acidity",
        "mlf acidity",
        "slow ripening",
        "slower ripening",
        "tartaric acid"
      ],
      "knowledge_graph_boost_applied": true,
      "why_retrieved": [
        "matched canonical/query terms: acid, acidity, affect, balance, climate, cool, freshness, length",
        "aligns with cause_effect reasoning intent",
        "matched SAT/tasting vocabulary",
        "supports cause/effect explanation",
        "matches knowledge-map concept or relationship terms",
        "matches knowledge-map causal-chain mechanism",
        "matches knowledge-map concept vocabulary",
        "official WSET extracted Tutor support",
        "matched official section/topic metadata",
        "exact term match"
      ],
      "text_excerpt": "# 7 Common Elements in Winemaking and Maturation <!-- página 52 --> COMMONE LEMENTISN W INEMAKINGAN D MATURATION 43 CommoEnl ementisn W inemakinagn dM aturation 7 There are certain factors and processes that are common to all wines and these are explored in this chapter. It is important to get an appreciation of their roles in winemaking and maturation an...",
      "scoring_breakdown": {
        "lexical_overlap": 0.18,
        "expanded_lexical_overlap": 0.0727,
        "canonical_dictionary_terms": 0.08,
        "dictionary_category_match": 0.0,
        "golden_chunk_boost": 0.0,
        "reasoning_type_alignment": 0.091,
        "pedagogical_role_alignment": 0.0,
        "retrieval_priority_boost": 0.0,
        "sat_term_boost": 0.09,
        "cause_effect_boost": 0.1,
        "exam_strategy_boost": 0.0,
        "knowledge_graph_match": 0.1,
        "causal_chain_match": 0.0533,
        "concept_match": 0.06,
        "source_concept_phrase_match": 0.0,
        "official_source_boost": 0.18,
        "exact_term_match_boost": 0.08,
        "section_topic_match_boost": 0.0267,
        "official_exam_register_boost": 0.06,
        "quality_flags_penalty": -0.0
      },
      "safe_for_examiner": false,
      "agent_corpus": "tutor"
    },
    {
      "chunk_id": "OFFICIAL_WSET_7_2_42_SPARKLING_WINES_OF_THE_WORLD_001",
      "score": 1.0,
      "source_video": "",
      "source_filename": "7-2_42_sparkling_wines_of_the_world.md",
      "source_type": "official_wset_extracted",
      "source_file": "knowledge/official-wset/study-guide/wset_markdown/seccion_7_section_4_sparkling_wines_of_the_world/7-2_42_sparkling_wines_of_the_world.md",
      "source_trust_tier": 1,
      "title": "42 Sparkling Wines of the World",
      "section": "7",
      "subtopic": "7.2",
      "official_grading_authority": false,
      "requires_human_review": true,
      "reasoning_type": "cause_effect",
      "pedagogical_role": "official_reference",
      "retrieval_priority": "none",
      "matched_terms": [
        "acid",
        "acidity",
        "balance",
        "climate",
        "cool",
        "high acidity",
        "length"
      ],
      "matched_concepts": [
        "Acidity",
        "acidity",
        "balance",
        "high acidity"
      ],
      "matched_causal_chains": [
        "Cool climate → high acidity in finished wine",
        "Cool climate → limited sugar accumulation → lower potential alcohol",
        "acidity",
        "high acidity",
        "length"
      ],
      "matched_dictionary_terms": [
        "acidity",
        "climate"
      ],
      "query_expansion_terms": [
        "acid",
        "acid retention",
        "acidity",
        "acidity 01",
        "acidity ageability",
        "balance",
        "climate",
        "cold climate",
        "cool climate",
        "cool climate 01",
        "cool climate 02",
        "cool climate acidity",
        "cool climate alcohol",
        "cool climate aroma",
        "cool climate under ripe",
        "cool climate wines always have green, unripe flavours.",
        "cool climate wines are always low in alcohol.",
        "cool climate → high acidity in finished wine",
        "cool climate → limited sugar accumulation → lower potential alcohol",
        "cool climate → slower ripening → primary aroma profile (citrus/green fruit/floral)",
        "crispness",
        "freshness",
        "growing season",
        "high acidity",
        "high acidity in a wine means the wine is low quality or unpleasant.",
        "high altitude",
        "higher acidity",
        "intensity",
        "length",
        "low temperature",
        "low temperatures",
        "lower ph",
        "malic acid",
        "malolactic conversion",
        "malolactic conversion acidity",
        "mlf acidity",
        "slow ripening",
        "slower ripening",
        "tartaric acid"
      ],
      "knowledge_graph_boost_applied": true,
      "why_retrieved": [
        "matched canonical/query terms: acid, acidity, balance, climate, cool, high acidity, length",
        "aligns with cause_effect reasoning intent",
        "matched SAT/tasting vocabulary",
        "supports cause/effect explanation",
        "matches knowledge-map concept or relationship terms",
        "matches knowledge-map causal-chain mechanism",
        "matches knowledge-map concept vocabulary",
        "official WSET extracted Tutor support",
        "matched official section/topic metadata",
        "exact term match"
      ],
      "text_excerpt": "# 42 Sparkling Wines of the World <!-- página 188 --> SPARKLING WINES OF THE WORLD 179 SparklinWg ineso ft heW orld C~ampagne remains th~ m~st prestigiou_ss parkling wine and consequently 1tw ill be treated m the greatest detail here. Such is its reputation that most premium sparkling wines are not only made in the same way but also using the same grape v...",
      "scoring_breakdown": {
        "lexical_overlap": 0.135,
        "expanded_lexical_overlap": 0.0509,
        "canonical_dictionary_terms": 0.08,
        "dictionary_category_match": 0.0,
        "golden_chunk_boost": 0.0,
        "reasoning_type_alignment": 0.091,
        "pedagogical_role_alignment": 0.0,
        "retrieval_priority_boost": 0.0,
        "sat_term_boost": 0.09,
        "cause_effect_boost": 0.1,
        "exam_strategy_boost": 0.0,
        "knowledge_graph_match": 0.1,
        "causal_chain_match": 0.0444,
        "concept_match": 0.06,
        "source_concept_phrase_match": 0.0,
        "official_source_boost": 0.18,
        "exact_term_match_boost": 0.08,
        "section_topic_match_boost": 0.0133,
        "official_exam_register_boost": 0.0,
        "quality_flags_penalty": -0.0
      },
      "safe_for_examiner": false,
      "agent_corpus": "tutor"
    },
    {
      "chunk_id": "OFFICIAL_WSET_OF_THE_WORLD_6_10_21_SOUTHERN_FRANCE_001",
      "score": 1.0,
      "source_video": "",
      "source_filename": "6-10_21_southern_france.md",
      "source_type": "official_wset_extracted",
      "source_file": "knowledge/official-wset/study-guide/wset_markdown/seccion_6_section_3_still_wines_of_the_world/6-10_21_southern_france.md",
      "source_trust_tier": 1,
      "title": "21 Southern France",
      "section": "6",
      "subtopic": "6.10",
      "official_grading_authority": false,
      "requires_human_review": true,
      "reasoning_type": "cause_effect",
      "pedagogical_role": "official_reference",
      "retrieval_priority": "none",
      "matched_terms": [
        "acidity",
        "climate",
        "cool",
        "growing season",
        "high acidity"
      ],
      "matched_concepts": [
        "Acidity",
        "Cool Climate",
        "acidity",
        "growing season",
        "high acidity"
      ],
      "matched_causal_chains": [
        "Cool climate → high acidity in finished wine",
        "Cool climate → limited sugar accumulation → lower potential alcohol",
        "Cool climate → slower ripening → primary aroma profile (citrus/green fruit/floral)",
        "acidity",
        "growing season",
        "high acidity"
      ],
      "matched_dictionary_terms": [
        "acidity",
        "climate"
      ],
      "query_expansion_terms": [
        "acid",
        "acid retention",
        "acidity",
        "acidity 01",
        "acidity ageability",
        "balance",
        "climate",
        "cold climate",
        "cool climate",
        "cool climate 01",
        "cool climate 02",
        "cool climate acidity",
        "cool climate alcohol",
        "cool climate aroma",
        "cool climate under ripe",
        "cool climate wines always have green, unripe flavours.",
        "cool climate wines are always low in alcohol.",
        "cool climate → high acidity in finished wine",
        "cool climate → limited sugar accumulation → lower potential alcohol",
        "cool climate → slower ripening → primary aroma profile (citrus/green fruit/floral)",
        "crispness",
        "freshness",
        "growing season",
        "high acidity",
        "high acidity in a wine means the wine is low quality or unpleasant.",
        "high altitude",
        "higher acidity",
        "intensity",
        "length",
        "low temperature",
        "low temperatures",
        "lower ph",
        "malic acid",
        "malolactic conversion",
        "malolactic conversion acidity",
        "mlf acidity",
        "slow ripening",
        "slower ripening",
        "tartaric acid"
      ],
      "knowledge_graph_boost_applied": true,
      "why_retrieved": [
        "matched canonical/query terms: acidity, climate, cool, growing season, high acidity",
        "aligns with cause_effect reasoning intent",
        "matched SAT/tasting vocabulary",
        "supports cause/effect explanation",
        "matches knowledge-map concept or relationship terms",
        "matches knowledge-map causal-chain mechanism",
        "matches knowledge-map concept vocabulary",
        "official WSET extracted Tutor support",
        "matched official section/topic metadata",
        "exact term match"
      ],
      "text_excerpt": "# 21 Southern France <!-- página 114 --> SOUTHERN FRANCE 105 SoutherFnr ance The vineyards of southern France lie along the Mediterranean coast 21 from Italy in the east to the Spanish border in the west. They are split into three broad areas: Languedoc and Roussillon to the west of the Rhone, and Provence to the east. The prevalence of the local IGP, Pay...",
      "scoring_breakdown": {
        "lexical_overlap": 0.135,
        "expanded_lexical_overlap": 0.0382,
        "canonical_dictionary_terms": 0.08,
        "dictionary_category_match": 0.0,
        "golden_chunk_boost": 0.0,
        "reasoning_type_alignment": 0.091,
        "pedagogical_role_alignment": 0.0,
        "retrieval_priority_boost": 0.0,
        "sat_term_boost": 0.09,
        "cause_effect_boost": 0.1,
        "exam_strategy_boost": 0.0,
        "knowledge_graph_match": 0.1,
        "causal_chain_match": 0.0533,
        "concept_match": 0.06,
        "source_concept_phrase_match": 0.0,
        "official_source_boost": 0.18,
        "exact_term_match_boost": 0.08,
        "section_topic_match_boost": 0.0133,
        "official_exam_register_boost": 0.0,
        "quality_flags_penalty": -0.0
      },
      "safe_for_examiner": false,
      "agent_corpus": "tutor"
    },
    {
      "chunk_id": "-P74Qh-YnNA-0002",
      "score": 0.8811,
      "source_video": "Loire Valley Wine Basics: Muscadet & Melon Blanc Explained - WSET & Wine Lover Guide",
      "source_filename": "",
      "source_type": "youtube_transcript",
      "source_file": "",
      "source_trust_tier": "pedagogical",
      "title": "",
      "section": "",
      "subtopic": "",
      "official_grading_authority": false,
      "requires_human_review": false,
      "reasoning_type": "cause_effect",
      "pedagogical_role": "theory_explanation",
      "retrieval_priority": "none",
      "matched_terms": [
        "climate",
        "cool",
        "cool climate"
      ],
      "matched_concepts": [
        "Acidity",
        "Cool Climate",
        "cool climate"
      ],
      "matched_causal_chains": [
        "Cool climate → high acidity in finished wine",
        "Cool climate → limited sugar accumulation → lower potential alcohol",
        "Cool climate → slower ripening → primary aroma profile (citrus/green fruit/floral)",
        "cool climate"
      ],
      "matched_dictionary_terms": [
        "climate",
        "cool climate"
      ],
      "query_expansion_terms": [
        "acid",
        "acid retention",
        "acidity",
        "acidity 01",
        "acidity ageability",
        "balance",
        "climate",
        "cold climate",
        "cool climate",
        "cool climate 01",
        "cool climate 02",
        "cool climate acidity",
        "cool climate alcohol",
        "cool climate aroma",
        "cool climate under ripe",
        "cool climate wines always have green, unripe flavours.",
        "cool climate wines are always low in alcohol.",
        "cool climate → high acidity in finished wine",
        "cool climate → limited sugar accumulation → lower potential alcohol",
        "cool climate → slower ripening → primary aroma profile (citrus/green fruit/floral)",
        "crispness",
        "freshness",
        "growing season",
        "high acidity",
        "high acidity in a wine means the wine is low quality or unpleasant.",
        "high altitude",
        "higher acidity",
        "intensity",
        "length",
        "low temperature",
        "low temperatures",
        "lower ph",
        "malic acid",
        "malolactic conversion",
        "malolactic conversion acidity",
        "mlf acidity",
        "slow ripening",
        "slower ripening",
        "tartaric acid"
      ],
      "knowledge_graph_boost_applied": true,
      "why_retrieved": [
        "matched canonical/query terms: climate, cool, cool climate",
        "aligns with cause_effect reasoning intent",
        "pedagogical role fits cause_effect_explanation",
        "matched SAT/tasting vocabulary",
        "supports cause/effect explanation",
        "matches knowledge-map concept or relationship terms",
        "matches knowledge-map causal-chain mechanism",
        "matches knowledge-map concept vocabulary",
        "contains the source concept phrase from the query",
        "exact term match",
        "quality flags reduced the score and require review"
      ],
      "text_excerpt": "So that map is now uh sort of transposed on a couple of pictures there on the left hand side the nonte vineyard. So that would be the red area on the far western side and then um the sair uh in the right hand picture which is the blue part of your previous map also transposed on that. Overall the climate is cold okay across all the areas but the central v...",
      "scoring_breakdown": {
        "lexical_overlap": 0.09,
        "expanded_lexical_overlap": 0.0145,
        "canonical_dictionary_terms": 0.08,
        "dictionary_category_match": 0.0,
        "golden_chunk_boost": 0.0,
        "reasoning_type_alignment": 0.091,
        "pedagogical_role_alignment": 0.1,
        "retrieval_priority_boost": 0.0,
        "sat_term_boost": 0.09,
        "cause_effect_boost": 0.1,
        "exam_strategy_boost": 0.0,
        "knowledge_graph_match": 0.075,
        "causal_chain_match": 0.0356,
        "concept_match": 0.045,
        "source_concept_phrase_match": 0.12,
        "official_source_boost": 0.0,
        "exact_term_match_boost": 0.08,
        "section_topic_match_boost": 0.0,
        "official_exam_register_boost": 0.0,
        "quality_flags_penalty": -0.04
      },
      "safe_for_examiner": false,
      "agent_corpus": "tutor"
    }
  ],
  "matched_causal_chain_nodes": [
    {
      "node_type": "causal_chain",
      "node_id": "CC_COOL_CLIMATE_ACIDITY",
      "chain_id": "CC_COOL_CLIMATE_ACIDITY",
      "chain_name": "Cool climate → high acidity in finished wine",
      "topic": "cool climate and acidity retention",
      "trigger_keywords": [
        "cool climate",
        "cold climate",
        "high altitude",
        "acidity",
        "freshness",
        "acid retention",
        "slow ripening"
      ],
      "steps": [
        {
          "step": 1,
          "label": "cause",
          "text": "Cool growing environment (lower temperatures, high altitude, or high-latitude location)"
        },
        {
          "step": 2,
          "label": "mechanism",
          "text": "Slow ripening delays sugar accumulation and preserves natural grape acids (malic and tartaric), reducing the rate at which malic acid is metabolised before harvest"
        },
        {
          "step": 3,
          "label": "effect",
          "text": "Wines retain higher acidity, show freshness and crispness, and typically have lower alcohol levels"
        },
        {
          "step": 4,
          "label": "exam_formulation",
          "text": "Cool climates slow ripening, preserving acidity and producing wines with higher acidity, freshness, and lower alcohol levels."
        }
      ],
      "starting_factor": {
        "concept_id": "C_COOL_CLIMATE",
        "description": "Growing season temperatures are at the lower end of what allows full grape ripening."
      },
      "intermediate_steps": [
        {
          "step_number": 1,
          "concept_id": "C_COOL_CLIMATE",
          "description": "Low temperatures slow the rate of photosynthesis and grape ripening.",
          "relationship_type": "causes"
        },
        {
          "step_number": 2,
          "concept_id": "C_ACIDITY",
          "description": "Slower ripening means malic acid (which degrades enzymatically as grapes ripen) is retained at higher levels at harvest. Tartaric acid, being stable, remains constant regardless of ripening speed.",
          "relationship_type": "increases"
        },
        {
          "step_number": 3,
          "concept_id": "C_ACIDITY",
          "description": "Lower sugar accumulation at harvest results in lower potential alcohol, meaning less dilution of acid perception in the finished wine.",
          "relationship_type": "influences"
        }
      ],
      "final_outcome": {
        "concept_id": "C_ACIDITY",
        "description": "Higher total acidity and lower pH in the finished wine, perceived as freshness and crispness on the palate."
      },
      "sat_relevance": "Use when justifying high acidity as a positive structural element in SAT quality assessment. High acidity in a cool-climate context is a feature, not a fault — link it to freshness, food-pairing versatility, and ageing potential.",
      "linked_misconceptions": [
        "MC_ACIDITY_01",
        "MC_COOL_CLIMATE_02"
      ],
      "linked_topics": [
        "T_RA1_CLIMATE_VITICULTURE"
      ],
      "examples": [
        {
          "region_or_wine": "Mosel Riesling Spätlese",
          "description": "Cool Mosel valley temperatures result in high residual malic acid and characteristically high total acidity, providing structure and longevity even in wines with significant residual sugar."
        },
        {
          "region_or_wine": "Champagne base wines",
          "description": "Cool Champagne climate produces high-acidity, low-alcohol base wines — intentionally sought because secondary fermentation and dosage add sweetness that must be balanced by this natural acidity."
        }
      ],
      "related_exam_questions": [
        "Explain how climate affects the acidity of a finished wine.",
        "Why do cool-climate wines tend to have higher acidity than warm-climate wines from the same grape variety?",
        "Describe the relationship between ripening rate and acid retention in grapes."
      ],
      "distinction_note": "A Distinction answer explains the mechanism (malic acid degradation rate during ripening) not merely the correlation (cool climate = high acidity). It also notes that tartaric acid behaves differently from malic acid, and may mention diurnal variation as a nuancing factor.",
      "complexity": "moderate",
      "exam_relevance": "critical",
      "tutor_use": true,
      "examiner_use": false,
      "agent_corpus": "tutor",
      "safe_for_examiner": false,
      "examiner_scoring_allowed": false,
      "requires_human_review": true,
      "governance": {
        "safe_for_examiner": false,
        "examiner_scoring_allowed": false,
        "agent_corpus": "tutor"
      },
      "_meta": {
        "schema_version": "causal_chain_v1",
        "created_date": "2026-05-13",
        "updated_date": "2026-05-15",
        "ingestion_status": "draft"
      },
      "id": "CC_COOL_CLIMATE_ACIDITY",
      "type": "causal_chain"
    },
    {
      "chain_id": "CC_COOL_CLIMATE_ALCOHOL",
      "chain_name": "Cool climate → limited sugar accumulation → lower potential alcohol",
      "starting_factor": {
        "concept_id": "C_COOL_CLIMATE",
        "description": "In cool climates, the rate of photosynthesis and sugar accumulation in grape berries is lower than in warm climates due to reduced temperature-driven metabolic activity."
      },
      "intermediate_steps": [
        {
          "step_number": 1,
          "concept_id": "C_COOL_CLIMATE",
          "description": "Photosynthesis produces sucrose in the leaves, which is transported to the grape berries as glucose and fructose. Lower temperatures reduce the rate of photosynthesis and, critically, the rate at which sugars accumulate in the berry during the ripening period.",
          "relationship_type": "causes"
        },
        {
          "step_number": 2,
          "concept_id": "C_COOL_CLIMATE",
          "description": "Shorter growing seasons in cool regions (e.g., Champagne, Mosel, English Vineyards) further limit total sugar accumulation time. The growing season ends when temperatures drop or when rain increases fungal disease risk — often before sugars reach warm-climate levels.",
          "relationship_type": "influences"
        },
        {
          "step_number": 3,
          "concept_id": "C_COOL_CLIMATE",
          "description": "Lower sugar at harvest translates directly to lower potential alcohol. Typical cool-climate base wines for sparkling production (Champagne, English sparkling) have 9.5–10.5% potential alcohol before secondary fermentation. For comparison, warm-climate reds routinely reach 14–15%+ naturally.",
          "relationship_type": "produces"
        }
      ],
      "final_outcome": {
        "concept_id": "C_COOL_CLIMATE",
        "description": "Lower alcohol level in the finished wine (7–12% typical range for fully fermented cool-climate styles). This contributes to wine freshness, lower caloric content, and greater perceived acidity. For sparkling wine base wines, low natural alcohol is a deliberate quality objective."
      },
      "examples": [
        {
          "region_or_wine": "Champagne NV base wine blend",
          "description": "Intentionally harvested at low ripeness for potential alcohol of 9.5–10% before secondary fermentation. The resulting 12–12.5% abv after tirage is considered ideal — the low base wine alcohol preserves acidity and freshness."
        },
        {
          "region_or_wine": "Mosel Kabinett Riesling",
          "description": "The lightest Prädikat level, harvested with minimum ripeness requirements. At 7–8% abv (with residual sugar), Kabinett exemplifies the cool climate's limited sugar accumulation used deliberately to produce a delicate, low-alcohol style."
        }
      ],
      "related_exam_questions": [
        "Why do cool-climate regions tend to produce wines with lower alcohol levels?",
        "Why is low natural alcohol a desirable quality in Champagne base wines?",
        "Describe the relationship between growing season temperature and sugar accumulation in grapes."
      ],
      "distinction_note": "A Distinction answer explains the photosynthesis mechanism, notes the additional constraint of shorter growing season length, distinguishes potential alcohol at harvest from final abv (which can be modified by winemaking), and gives a concrete abv range for a specific cool-climate style.",
      "complexity": "simple",
      "exam_relevance": "high",
      "tutor_use": true,
      "examiner_use": false,
      "_meta": {
        "schema_version": "1.0",
        "created_date": "2026-05-13",
        "ingestion_status": "draft"
      },
      "node_id": "CC_COOL_CLIMATE_ALCOHOL",
      "id": "CC_COOL_CLIMATE_ALCOHOL",
      "node_type": "causal_chain",
      "type": "causal_chain",
      "safe_for_examiner": false,
      "examiner_scoring_allowed": false,
      "agent_corpus": "tutor"
    },
    {
      "chain_id": "CC_COOL_CLIMATE_AROMA",
      "chain_name": "Cool climate → slower ripening → primary aroma profile (citrus/green fruit/floral)",
      "starting_factor": {
        "concept_id": "C_COOL_CLIMATE",
        "description": "In cool growing regions, lower temperatures slow the enzymatic ripening processes in the grape, resulting in a different terpene and aroma precursor profile at harvest."
      },
      "intermediate_steps": [
        {
          "step_number": 1,
          "concept_id": "C_COOL_CLIMATE",
          "description": "Slower ripening means that the grape remains at lower sugar levels and higher acidity for a longer portion of the growing season. During this extended period, aromatic precursors develop that would be destroyed or transformed at higher temperatures.",
          "relationship_type": "causes"
        },
        {
          "step_number": 2,
          "concept_id": "C_COOL_CLIMATE",
          "description": "Higher methoxypyrazine concentrations survive when ripening is slower and cooler (methoxypyrazines degrade enzymatically with heat and light exposure). In grapes prone to methoxypyrazines (Sauvignon Blanc, Cabernet Sauvignon), this produces herbaceous, green capsicum, or grassy notes — a regional signature when grapes are slightly under-ripe.",
          "relationship_type": "produces"
        },
        {
          "step_number": 3,
          "concept_id": "C_COOL_CLIMATE",
          "description": "When cool-climate grapes achieve full phenolic ripeness, the aroma profile is dominated by primary aromas of citrus (lemon, grapefruit, lime), stone fruit (green apple, pear, white peach), and floral notes (elderflower, blossom) rather than the tropical fruit and jam characters of warm-climate versions of the same variety.",
          "relationship_type": "produces"
        }
      ],
      "final_outcome": {
        "concept_id": "C_COOL_CLIMATE",
        "description": "Cool-climate wines show citrus, green fruit, and floral primary aromas when fully ripe, or herbaceous/green notes if under-ripe. This contrasts with warm-climate versions of the same variety which show tropical fruit, stone fruit jam, and sometimes cooked fruit characters."
      },
      "examples": [
        {
          "region_or_wine": "Marlborough Sauvignon Blanc vs. Californian Sauvignon Blanc",
          "description": "Cool Marlborough produces intense gooseberry, citrus, and herbaceous (cut grass) notes from retained methoxypyrazines and cool-climate aroma precursors. Warmer California Sauvignon Blanc tends toward melon, peach, and tropical fruit with far less herbal character."
        },
        {
          "region_or_wine": "Mosel Riesling vs. Clare Valley Riesling",
          "description": "Cool Mosel produces lime zest, green apple, and delicate floral notes. Warmer Clare Valley produces lime, but also tropical notes and a different mineral expression — the variety is the same, the climate shapes the fruit register."
        }
      ],
      "related_exam_questions": [
        "How does climate affect the primary aroma profile of a white wine?",
        "Why does Sauvignon Blanc from Marlborough often show more herbaceous character than Californian examples?",
        "Describe the difference in aroma profile between a cool-climate and warm-climate version of the same variety."
      ],
      "distinction_note": "A Distinction answer names methoxypyrazines as the compound responsible for herbaceous notes and explains their temperature-dependent degradation rate, contrasts specific citrus/floral vs. tropical descriptors for cool vs. warm climate, and names specific wine examples.",
      "complexity": "moderate",
      "exam_relevance": "critical",
      "tutor_use": true,
      "examiner_use": false,
      "_meta": {
        "schema_version": "1.0",
        "created_date": "2026-05-13",
        "ingestion_status": "draft"
      },
      "node_id": "CC_COOL_CLIMATE_AROMA",
      "id": "CC_COOL_CLIMATE_AROMA",
      "node_type": "causal_chain",
      "type": "causal_chain",
      "safe_for_examiner": false,
      "examiner_scoring_allowed": false,
      "agent_corpus": "tutor"
    }
  ],
  "summary_statistics": {
    "retrieved_count": 5,
    "reasoning_type_counts": {
      "cause_effect": 5
    },
    "pedagogical_role_counts": {
      "official_reference": 4,
      "theory_explanation": 1
    },
    "retrieval_priority_counts": {
      "none": 5
    }
  }
}
